README.md
setup.py
booster/__init__.py
booster/datastruct/__init__.py
booster/datastruct/aggregator.py
booster/datastruct/diagnostic.py
booster/evaluation/__init__.py
booster/evaluation/classification.py
booster/evaluation/evaluator.py
booster/evaluation/freebits.py
booster/evaluation/vi.py
booster/logging/__init__.py
booster/logging/datatracker.py
booster/logging/logger.py
booster/models/__init__.py
booster/models/vae.py
booster/pipeline/__init__.py
booster/pipeline/pipeline.py
booster/training/__init__.py
booster/training/ops.py
booster/training/scheduler.py
booster/training/trigger.py
booster/utils/__init__.py
booster/utils/ema.py
booster/utils/functional.py
booster/utils/schedule.py
booster_pytorch.egg-info/PKG-INFO
booster_pytorch.egg-info/SOURCES.txt
booster_pytorch.egg-info/dependency_links.txt
booster_pytorch.egg-info/requires.txt
booster_pytorch.egg-info/top_level.txt