Metadata-Version: 2.1
Name: booster-pytorch
Version: 0.0.2
Summary: A lightweight library to ease the training and the debugging of deep neural networks with PyTorch. Data structures and paradigms.
Home-page: https://github.com/vlievin/booster-pytorch
Author: Valentin Lievin
Author-email: valentin.lievin@gmail.com
License: UNKNOWN
Platform: UNKNOWN
Classifier: Programming Language :: Python :: 3
Classifier: License :: OSI Approved :: MIT License
Classifier: Operating System :: OS Independent
